multiworm/__init__.py
multiworm/blob.py
multiworm/core.py
multiworm/experiment.py
multiworm/filters.py
multiworm/util.py
multiworm/analytics/__init__.py
multiworm/analytics/analytics.py
multiworm/analytics/noise.py
multiworm/analytics/sgolay.py
multiworm/analytics/smooth.py
multiworm/analytics/speed.py
multiworm/readers/__init__.py
multiworm/readers/blob.py
multiworm/readers/image.py
multiworm/readers/summary.py
multiworm-0.1.1.dist-info/DESCRIPTION.rst
multiworm-0.1.1.dist-info/METADATA
multiworm-0.1.1.dist-info/RECORD
multiworm-0.1.1.dist-info/WHEEL
multiworm-0.1.1.dist-info/metadata.json
multiworm-0.1.1.dist-info/top_level.txt
