Metadata-Version: 2.0
Name: multiworm
Version: 0.1.1
Summary: Python interface for Multi-Worm Tracker data
Home-page: https://github.org/nicktimko/multiworm
Author: Nick Timkovich
Author-email: npt@u.northwestern.edu
License: UNKNOWN
Keywords: c. elegans,caenorhabditis elegans,caenorhabditis,elegans,worm,tracking,biology,amaral
Platform: UNKNOWN
Classifier: Development Status :: 5 - Production/Stable
Classifier: Intended Audience :: Science/Research
Classifier: License :: OSI Approved :: MIT License
Classifier: Topic :: Scientific/Engineering :: Bio-Informatics
Requires-Dist: networkx (>=1.8.1)
Requires-Dist: numpy (>=1.8.1)
Requires-Dist: pandas (>=0.14.0)
Requires-Dist: pathlib (>=1.0.1)
Requires-Dist: six (>=1.7.2)
